logtap/__init__.py
logtap/__main__.py
logtap/api/__init__.py
logtap/api/app.py
logtap/api/dependencies.py
logtap/api/routes/__init__.py
logtap/api/routes/files.py
logtap/api/routes/health.py
logtap/api/routes/logs.py
logtap/api/routes/parsed.py
logtap/cli/__init__.py
logtap/cli/commands/__init__.py
logtap/cli/commands/files.py
logtap/cli/commands/query.py
logtap/cli/commands/serve.py
logtap/cli/commands/tail.py
logtap/cli/main.py
logtap/core/__init__.py
logtap/core/parsers/__init__.py
logtap/core/parsers/apache.py
logtap/core/parsers/auto.py
logtap/core/parsers/base.py
logtap/core/parsers/json_parser.py
logtap/core/parsers/nginx.py
logtap/core/parsers/syslog.py
logtap/core/reader.py
logtap/core/search.py
logtap/core/validation.py
logtap/models/__init__.py
logtap/models/config.py
logtap/models/responses.py
logtap-0.2.2.dist-info/METADATA
logtap-0.2.2.dist-info/WHEEL
logtap-0.2.2.dist-info/entry_points.txt
logtap-0.2.2.dist-info/licenses/LICENSE
logtap-0.2.2.dist-info/RECORD
