Metadata-Version: 2.4
Name: logtap
Version: 0.2.2
Summary: A CLI-first log access tool for Unix systems. Remote log file access without SSH.
License: GPL-3.0-or-later
License-File: LICENSE
Keywords: logs,monitoring,cli,devops,sysadmin
Author: cainky
Author-email: kylecain.me@gmail.com
Requires-Python: >=3.10,<4.0
Classifier: Development Status :: 4 - Beta
Classifier: Environment :: Console
Classifier: Intended Audience :: Developers
Classifier: Intended Audience :: System Administrators
Classifier: License :: OSI Approved :: GNU General Public License v3 or later (GPLv3+)
Classifier: Operating System :: MacOS
Classifier: Operating System :: POSIX :: Linux
Classifier: Programming Language :: Python :: 3
Classifier: Programming Language :: Python :: 3.10
Classifier: Programming Language :: Python :: 3.11
Classifier: Programming Language :: Python :: 3.12
Classifier: Programming Language :: Python :: 3.13
Classifier: Programming Language :: Python :: 3.14
Classifier: Topic :: System :: Logging
Classifier: Topic :: System :: Monitoring
Classifier: Topic :: System :: Systems Administration
Requires-Dist: aiofiles (>=23.2.1)
Requires-Dist: fastapi (>=0.109.0)
Requires-Dist: httpx (>=0.26.0)
Requires-Dist: pydantic (>=2.5.0)
Requires-Dist: pydantic-settings (>=2.1.0)
Requires-Dist: python-dotenv (>=1.0.1)
Requires-Dist: rich (>=13.7.0)
Requires-Dist: typer[all] (>=0.9.0)
Requires-Dist: uvicorn[standard] (>=0.27.0)
Requires-Dist: websockets (>=12.0)
Project-URL: Homepage, https://github.com/cainky/logtap
Project-URL: Repository, https://github.com/cainky/logtap
